pickle_compression/__init__.py
pickle_compression/_version.py
pickle_compression/compression_utils.py
pickle_compression/lgbm_booster.py
pickle_compression/pickling.py
pickle_compression/sklearn_tree.py
pickle_compression-0.0.0.dist-info/METADATA
pickle_compression-0.0.0.dist-info/WHEEL
pickle_compression-0.0.0.dist-info/top_level.txt
pickle_compression-0.0.0.dist-info/RECORD
