Metadata-Version: 2.1
Name: pickle-compression
Version: 0.0.0
Summary: A python package for efficient pickling.
Home-page: https://github.com/pavelzw/pickle-compression
Author: Pavel Zwerschke
Author-email: pavelzw@gmail.com
Classifier: Programming Language :: Python :: 3
Classifier: Programming Language :: Python :: 3.8
Classifier: Programming Language :: Python :: 3.9
Classifier: Programming Language :: Python :: 3.10
Classifier: Programming Language :: Python :: 3.11
Requires-Python: >=3.8
Requires-Dist: numpy
Provides-Extra: lightgbm
Requires-Dist: lightgbm ; extra == 'lightgbm'
Provides-Extra: scikit-learn
Requires-Dist: scikit-learn ; extra == 'scikit-learn'
